wagtail_editable_help/__init__.py
wagtail_editable_help/apps.py
wagtail_editable_help/middleware.py
wagtail_editable_help/models.py
wagtail_editable_help/wagtail_hooks.py
wagtail_editable_help/migrations/0001_initial.py
wagtail_editable_help/migrations/__init__.py
wagtail_editable_help/static/wagtail_editable_help/wagtail_editable_help.css
wagtail_editable_help-0.2.0.dist-info/LICENSE
wagtail_editable_help-0.2.0.dist-info/WHEEL
wagtail_editable_help-0.2.0.dist-info/METADATA
wagtail_editable_help-0.2.0.dist-info/RECORD
