Metadata-Version: 2.1
Name: wagtail-editable-help
Version: 0.2.0
Summary: Make help text editable in the Wagtail admin
Author-email: Matt Westcott <matthew@torchbox.com>
Requires-Python: >=3.8
Classifier: Development Status :: 3 - Alpha
Classifier: Intended Audience :: Developers
Classifier: License :: OSI Approved :: BSD License
Classifier: Operating System :: OS Independent
Classifier: Programming Language :: Python
Classifier: Programming Language :: Python :: 3
Classifier: Programming Language :: Python :: 3.8
Classifier: Programming Language :: Python :: 3.9
Classifier: Programming Language :: Python :: 3.10
Classifier: Programming Language :: Python :: 3.11
Classifier: Programming Language :: Python :: 3.12
Classifier: Framework :: Django
Classifier: Framework :: Django :: 3.2
Classifier: Framework :: Django :: 4.1
Classifier: Framework :: Django :: 4.2
Classifier: Framework :: Wagtail
Classifier: Framework :: Wagtail :: 2
Classifier: Framework :: Wagtail :: 3
Classifier: Framework :: Wagtail :: 4
Classifier: Framework :: Wagtail :: 5
Requires-Dist: Django>=3.2
Requires-Dist: wagtail>=4.1
Requires-Dist: telepath>=0.3
Requires-Dist: dj-database-url==0.5.0 ; extra == "testing"
Requires-Dist: freezegun==0.3.15 ; extra == "testing"
Project-URL: Documentation, https://github.com/wagtail/wagtail-editable-help#readme
Project-URL: Source, https://github.com/wagtail/wagtail-editable-help
Provides-Extra: testing
